toyotama/__init__.py
toyotama/ad/__init__.py
toyotama/ad/util.py
toyotama/connect/__init__.py
toyotama/connect/process.py
toyotama/connect/socket.py
toyotama/connect/tube.py
toyotama/crypto/__init__.py
toyotama/crypto/aes.py
toyotama/crypto/classical_cipher.py
toyotama/crypto/curve.py
toyotama/crypto/hash/sha256.py
toyotama/crypto/rng.py
toyotama/crypto/rsa.py
toyotama/crypto/util.py
toyotama/elf/__init__.py
toyotama/elf/chall
toyotama/elf/const.py
toyotama/elf/elf.py
toyotama/elf/elfstruct.py
toyotama/elf/parser.py
toyotama/pwn/__init__.py
toyotama/pwn/address.py
toyotama/pwn/const.py
toyotama/pwn/fsa.py
toyotama/pwn/payload.py
toyotama/pwn/util.py
toyotama/terminal/__init__.py
toyotama/terminal/style.py
toyotama/util/__init__.py
toyotama/util/bitstream.py
toyotama/util/convert.py
toyotama/util/decompress.py
toyotama/util/input.py
toyotama/util/integer.py
toyotama/util/log.py
toyotama/util/shell.py
toyotama/util/util.py
toyotama/web/__init__.py
toyotama/web/util.py
toyotama-0.9.10.dist-info/LICENSE
toyotama-0.9.10.dist-info/METADATA
toyotama-0.9.10.dist-info/WHEEL
toyotama-0.9.10.dist-info/entry_points.txt
toyotama-0.9.10.dist-info/RECORD
